contentconvertor/__init__.py
contentconvertor/tweet2gram.py
contentconvertor-0.2.3.dist-info/LICENSE
contentconvertor-0.2.3.dist-info/METADATA
contentconvertor-0.2.3.dist-info/WHEEL
contentconvertor-0.2.3.dist-info/top_level.txt
contentconvertor-0.2.3.dist-info/RECORD
